{
  "AddonUUID": "2c199913-dba2-4533-ad78-747b6553acf8",
  "AddonVersion": "0.0.16",
  "DebugPort": 4500,
  "WebappBaseUrl": "https://app.sandbox.pepperi.com",
  "DefaultEditor": "main",
  "Endpoints": [
    "installation.ts",
    "api.ts"
  ],
  "Editors": [
    "main"
  ],
  "PublishConfig": {
    "ClientStack": "ng10",
    "Editors": [
      {
        "ParentPackageName": "training",
        "PackageName": "Todos",
        "Description": "Dor's new Todos"
      }
    ],
    "Dependencies": {},
    "CPISide": []
  }
}
